sencore/__init__.py
sencore/_usage.py
sencore/deeplapi.py
sencore/entry.py
sencore/kg_parser.py
sencore/lib.py
sencore/parser.py
sencore/phrase_model_parser.py
sencore/phrase_parser.py
sencore/structure_parser.py
sencore/train.py
sencore/vocab_parser/__init__.py
sencore/vocab_parser/en.py
sencore/vocab_parser/es.py
sencore/vocab_parser/general.py
sencore-0.1.56.dist-info/METADATA
sencore-0.1.56.dist-info/WHEEL
sencore-0.1.56.dist-info/entry_points.txt
sencore-0.1.56.dist-info/RECORD
