Metadata-Version: 2.3
Name: sencore
Version: 0.1.56
Summary: sentence nlp parser for multilingua
Keywords: NLP,sentence parsing,spacy
Author: Phoenix Grey
Author-email: phoenix.grey0108@gmail.com
Requires-Python: >=3.12,<4.0
Classifier: Programming Language :: Python :: 3
Classifier: Programming Language :: Python :: 3.12
Classifier: Programming Language :: Python :: 3.13
Requires-Dist: click (>=8.0.3,<9.0.0)
Requires-Dist: deepl (==1.20.0)
Requires-Dist: kg-detective (==0.1.29)
Requires-Dist: numpy (==1.26.4)
Requires-Dist: phrase-detective (==0.1.35)
Requires-Dist: spacy (==3.7.5)
Requires-Dist: structure-detective (==0.1.9)
Requires-Dist: transformers (==4.47.1)
Project-URL: Documentation, https://qishe-nlp.github.io/sencore/
Project-URL: Repository, https://github.com/qishe-nlp/sencore
